morpheus_core/__init__.py
morpheus_core/__version__.py
morpheus_core/morpheus_core.py
morpheus_core/helpers/__init__.py
morpheus_core/helpers/fits_helper.py
morpheus_core/helpers/label_helper.py
morpheus_core/helpers/misc_helper.py
morpheus_core/helpers/parallel_helper.py
morpheus_core-0.1.13.dist-info/LICENSE
morpheus_core-0.1.13.dist-info/METADATA
morpheus_core-0.1.13.dist-info/WHEEL
morpheus_core-0.1.13.dist-info/top_level.txt
morpheus_core-0.1.13.dist-info/RECORD
