Metadata-Version: 2.1
Name: morpheus-core
Version: 0.1.13
Summary: A framework for scaling pixel-level analysis to large images
Home-page: https://github.com/morpheus-project/morpheus-core
Author: Ryan Hausen & Brant Robertson
Author-email: rhausen@ucsc.edu
License: MIT
Classifier: Programming Language :: Python
Classifier: Programming Language :: Python :: 3
Classifier: Programming Language :: Python :: 3.6
Classifier: Programming Language :: Python :: Implementation :: PyPy
Classifier: License :: OSI Approved :: MIT License
Classifier: Intended Audience :: Science/Research
Classifier: Development Status :: 4 - Beta
Classifier: Operating System :: POSIX :: Linux
Classifier: Topic :: Scientific/Engineering
Requires-Python: >=3.6
License-File: LICENSE
Requires-Dist: dill
Requires-Dist: numpy
Requires-Dist: astropy
Requires-Dist: tqdm
